mlx_cluster/__init__.py
mlx_cluster/_ext.cpython-311-darwin.so
mlx_cluster/libmlx.dylib
mlx_cluster/libmlx_cluster.dylib
mlx_cluster/mlx_cluster.metallib
mlx_cluster-0.0.25.dist-info/LICENSE
mlx_cluster-0.0.25.dist-info/METADATA
mlx_cluster-0.0.25.dist-info/WHEEL
mlx_cluster-0.0.25.dist-info/top_level.txt
mlx_cluster-0.0.25.dist-info/RECORD
