Metadata-Version: 2.1
Name: mlx_cluster
Version: 0.0.25
Summary: C++ and Metal extensions for MLX CTC Loss
Author-email: Vinay Pandya <vinayharshadpandya27@gmail.com>
Project-URL: Homepage, https://github.com/vinayhpandya/mlx_cluster
Project-URL: Issues, https://github.com/vinayhpandya/mlx_cluster/Issues
Classifier: Development Status :: 3 - Alpha
Classifier: Programming Language :: Python :: 3
Classifier: Programming Language :: C++
Classifier: License :: OSI Approved :: MIT License
Classifier: Operating System :: OS Independent
Requires-Python: >=3.8
License-File: LICENSE
Provides-Extra: dev
Provides-Extra: test
Requires-Dist: pytest ==7.4.4 ; extra == 'test'
Requires-Dist: scipy ==1.12.0 ; extra == 'test'
